[
    {
      "Sno": 1,
      "Name": "Thangaraj",
      "Employee Id": "NA",
      "Photo": "Employee Image",
      "Mobile": "9489093303",
      "Designation": "SO",
      "Zone": "zone 1",
      "Category": "Thirunagar colony",
      "Access": "supervisor",
      "Status": "active",
      "Action": ""
    },
    {
      "Sno": 2,
      "Name": "Satheesh R",
      "Employee Id": "NA",
      "Photo": "Employee Image",
      "Mobile": "8300681269",
      "Designation": "SI",
      "Zone": "zone 1",
      "Category": "Division 3",
      "Access": "supervisor",
      "Status": "active",
      "Action": ""
    },
    {
      "Sno": 3,
      "Name": "Vimal Raj/ Rathana kumar",
      "Employee Id": "NA",
      "Photo": "Employee Image",
      "Mobile": "8760871778",
      "Designation": "Incharge",
      "Zone": "zone 1",
      "Category": "Thirunagar colony(SHG/CW)",
      "Access": "incharge",
      "Status": "active",
      "Action": ""
    },
    {
      "Sno": 4,
      "Name": "MayilVaganan/NarayanaSamy",
      "Employee Id": "NA",
      "Photo": "Employee Image",
      "Mobile": "9942364653",
      "Designation": "Incharge",
      "Zone": "zone 1",
      "Category": "R.N Pudur(SHG/DRIVER)",
      "Access": "incharge",
      "Status": "active",
      "Action": ""
    },
    {
      "Sno": 5,
      "Name": "Gowtham/Duraisamy",
      "Employee Id": "NA",
      "Photo": "Employee Image",
      "Mobile": "9994071292",
      "Designation": "Incharge",
      "Zone": "zone 1",
      "Category": "R.N Pudur(SHG/CW)",
      "Access": "incharge",
      "Status": "active",
      "Action": ""
    },
    {
      "Sno": 6,
      "Name": "Kannan",
      "Employee Id": "NA",
      "Photo": "Employee Image",
      "Mobile": "9489093311",
      "Designation": "SI",
      "Zone": "zone 1",
      "Category": "R.N Pudur (Division -1)",
      "Access": "supervisor",
      "Status": "active",
      "Action": ""
    },
    {
      "Sno": 7,
      "Name": "Farman/Firose Ahamed",
      "Employee Id": "NA",
      "Photo": "Employee Image",
      "Mobile": "7639632883",
      "Designation": "Incharge",
      "Zone": "zone 1",
      "Category": "B.P Agraharam(SHG/CW)",
      "Access": "incharge",
      "Status": "active",
      "Action": ""
    },
    {
      "Sno": 8,
      "Name": "Luckeswaran/Mani",
      "Employee Id": "NA",
      "Photo": "Employee Image",
      "Mobile": "8248512809",
      "Designation": "Incharge",
      "Zone": "zone 1",
      "Category": "Veerappanchatram(SHG/CW)",
      "Access": "incharge",
      "Status": "inactive",
      "Action": ""
    },
    {
      "Sno": 9,
      "Name": "Karthikeyan/Ramasamy",
      "Employee Id": "00",
      "Photo": "Employee Image",
      "Mobile": "9787920197",
      "Designation": "SHG/CW",
      "Zone": "zone 1",
      "Category": "Veerappanchatram(SHG/CW)",
      "Access": "incharge",
      "Status": "active",
      "Action": ""
    },
    {
      "Sno": 10,
      "Name": "Mathanraj/Ponnuvel",
      "Employee Id": "NA",
      "Photo": "Employee Image",
      "Mobile": "9788084866",
      "Designation": "Incharge",
      "Zone": "zone 1",
      "Category": "B.P Agraharam(MCC/SHG)",
      "Access": "incharge",
      "Status": "active",
      "Action": ""
    },
    {
      "Sno": 11,
      "Name": "sundarrajan/subramani",
      "Employee Id": "NA",
      "Photo": "Employee Image",
      "Mobile": "8610880228",
      "Designation": "Incharge",
      "Zone": "zone 1",
      "Category": "Vairapalayam(MCC/SHG)",
      "Access": "incharge",
      "Status": "active",
      "Action": ""
    },
    {
      "Sno": 12,
      "Name": "Maheshwari/Ramasamy",
      "Employee Id": "00",
      "Photo": "Employee Image",
      "Mobile": "9047822062",
      "Designation": "Incharge",
      "Zone": "zone 1",
      "Category": "B.P Agraharam(PT/DBC)",
      "Access": "incharge",
      "Status": "active",
      "Action": ""
    },
    {
      "Sno": 13,
      "Name": "Sivaranjani/Raj",
      "Employee Id": "00",
      "Photo": "Employee Image",
      "Mobile": "8526289475",
      "Designation": "Incharge",
      "Zone": "zone 1",
      "Category": "R.N Pudur (PT/DBC)",
      "Access": "incharge",
      "Status": "active",
      "Action": ""
    },
    {
      "Sno": 14,
      "Name": "Balan / Kannappan",
      "Employee Id": "00",
      "Photo": "Employee Image",
      "Mobile": "9942640368",
      "Designation": "Incharge",
      "Zone": "zone 1",
      "Category": "Thirunagar colony(PER/CW)",
      "Access": "incharge",
      "Status": "active",
      "Action": ""
    },
    {
      "Sno": 15,
      "Name": "Veeran/ Ramachandran",
      "Employee Id": "00",
      "Photo": "Employee Image",
      "Mobile": "8098630016",
      "Designation": "Incharge",
      "Zone": "zone 1",
      "Category": "R.N Pudur(PER/CW)",
      "Access": "incharge",
      "Status": "active",
      "Action": ""
    },
    {
      "Sno": 16,
      "Name": "Kannan/Marimuthu",
      "Employee Id": "00",
      "Photo": "Employee Image",
      "Mobile": "9750297576",
      "Designation": "Incharge",
      "Zone": "zone 1",
      "Category": "Veerappanchatram(PER/CW)",
      "Access": "incharge",
      "Status": "active",
      "Action": ""
    },
    {
      "Sno": 17,
      "Name": "Moorthi/Chinnaraman",
      "Employee Id": "00",
      "Photo": "Employee Image",
      "Mobile": "9600598449",
      "Designation": "Incharge",
      "Zone": "zone 1",
      "Category": "B.P Agraharam(PER/CW)",
      "Access": "incharge",
      "Status": "active",
      "Action": ""
    },
    {
      "Sno": 18,
      "Name": "Boopathy",
      "Employee Id": "NA",
      "Photo": "Employee Image",
      "Mobile": "9489093292",
      "Designation": "SO",
      "Zone": "zone 2",
      "Category": "Zone -2",
      "Access": "supervisor",
      "Status": "active",
      "Action": ""
    },
    {
      "Sno": 19,
      "Name": "Manivel P",
      "Employee Id": "NA",
      "Photo": "Employee Image",
      "Mobile": "9489093254",
      "Designation": "SI",
      "Zone": "zone 2",
      "Category": "Zone-2",
      "Access": "supervisor",
      "Status": "active",
      "Action": ""
    },
    {
      "Sno": 20,
      "Name": "Prakash/Gurusamy",
      "Employee Id": "00000",
      "Photo": "Employee Image",
      "Mobile": "9361575676",
      "Designation": "incharge",
      "Zone": "zone 2",
      "Category": "RKV.Road market(PT/DBC)",
      "Access": "incharge",
      "Status": "active",
      "Action": ""
    },
    {
      "Sno": 21,
      "Name": "Manimegalai/Sivasakthi",
      "Employee Id": "00",
      "Photo": "Employee Image",
      "Mobile": "9791867582",
      "Designation": "PT/DBC",
      "Zone": "zone 2",
      "Category": "periyasemur(PT/DBC)",
      "Access": "incharge",
      "Status": "active",
      "Action": ""
    }
  ]
  